sure_pypi_test/__init__.py
sure_pypi_test/main.py
sure_pypi_test/surego.py
sure_pypi_test-0.1.3.dist-info/LICENSE
sure_pypi_test-0.1.3.dist-info/METADATA
sure_pypi_test-0.1.3.dist-info/WHEEL
sure_pypi_test-0.1.3.dist-info/top_level.txt
sure_pypi_test-0.1.3.dist-info/RECORD
