Metadata-Version: 2.1
Name: sure-pypi-test
Version: 0.1.3
Summary: pypi打包测试
Home-page: https://github.com/me/myproject
Author: Sure Wong
Author-email: surewong.com@gmail.com
License: MIT
Classifier: License :: OSI Approved :: MIT License
Classifier: Programming Language :: Python
Classifier: Programming Language :: Python :: 3
Classifier: Programming Language :: Python :: 3.6
Classifier: Programming Language :: Python :: Implementation :: CPython
Classifier: Programming Language :: Python :: Implementation :: PyPy
Requires-Python: >=3.6.0
License-File: LICENSE
